{
  "trades": [
    {
      "id": "cmf2hut45006boe1c8x2g93y2",
      "userId": "dev-user-1",
      "symbol": "AAPL",
      "direction": "LONG",
      "entryPrice": 150,
      "positionSize": 10,
      "stopLoss": 145,
      "exitPrice": null,
      "status": "ACTIVE",
      "entryDate": "2025-09-02T11:57:48.389Z",
      "exitDate": null,
      "realizedPnL": null,
      "riskAmount": 50,
      "riskPercentage": 0.05,
      "notes": null,
      "alignmentScore": null,
      "alignmentLevel": null,
      "alignmentWarnings": null,
      "alignmentConfirmations": null,
      "createdAt": "2025-09-02T11:57:48.389Z",
      "updatedAt": "2025-09-02T11:57:48.389Z",
      "methodAnalysis": [],
      "mindsetTags": [],
      "outcome": "BREAKEVEN",
      "returnPercentage": 0
    }
  ],
  "statistics": {
    "totalTrades": 0,
    "winningTrades": 0,
    "losingTrades": 0,
    "breakevenTrades": 0,
    "winRate": 0,
    "lossRate": 0,
    "winLossRatio": 0,
    "totalPnL": 0,
    "averageProfit": 0,
    "averageLoss": 0,
    "averageTrade": 0,
    "expectancy": 0,
    "profitFactor": 0,
    "recoveryFactor": 0,
    "maxWin": 0,
    "maxLoss": 0,
    "maxConsecutiveWins": 0,
    "maxConsecutiveLosses": 0,
    "currentStreak": 0,
    "streakType": "NONE",
    "averageRisk": 0,
    "riskAdjustedReturn": 0,
    "maxDrawdown": 0,
    "sharpeRatio": 0,
    "averageHoldTime": 0,
    "tradingFrequency": 0,
    "bestMonth": "N/A",
    "worstMonth": "N/A"
  },
  "totalCount": 1,
  "filteredCount": 1,
  "comparisonStats": {
    "allTrades": {
      "totalTrades": 0,
      "winningTrades": 0,
      "losingTrades": 0,
      "breakevenTrades": 0,
      "winRate": 0,
      "lossRate": 0,
      "winLossRatio": 0,
      "totalPnL": 0,
      "averageProfit": 0,
      "averageLoss": 0,
      "averageTrade": 0,
      "expectancy": 0,
      "profitFactor": 0,
      "recoveryFactor": 0,
      "maxWin": 0,
      "maxLoss": 0,
      "maxConsecutiveWins": 0,
      "maxConsecutiveLosses": 0,
      "currentStreak": 0,
      "streakType": "NONE",
      "averageRisk": 0,
      "riskAdjustedReturn": 0,
      "maxDrawdown": 0,
      "sharpeRatio": 0,
      "averageHoldTime": 0,
      "tradingFrequency": 0,
      "bestMonth": "N/A",
      "worstMonth": "N/A"
    },
    "filtered": {
      "totalTrades": 0,
      "winningTrades": 0,
      "losingTrades": 0,
      "breakevenTrades": 0,
      "winRate": 0,
      "lossRate": 0,
      "winLossRatio": 0,
      "totalPnL": 0,
      "averageProfit": 0,
      "averageLoss": 0,
      "averageTrade": 0,
      "expectancy": 0,
      "profitFactor": 0,
      "recoveryFactor": 0,
      "maxWin": 0,
      "maxLoss": 0,
      "maxConsecutiveWins": 0,
      "maxConsecutiveLosses": 0,
      "currentStreak": 0,
      "streakType": "NONE",
      "averageRisk": 0,
      "riskAdjustedReturn": 0,
      "maxDrawdown": 0,
      "sharpeRatio": 0,
      "averageHoldTime": 0,
      "tradingFrequency": 0,
      "bestMonth": "N/A",
      "worstMonth": "N/A"
    },
    "improvement": 0
  }
}